createpypiproject
