Metadata-Version: 2.1
Name: create-pypi-project
Version: 0.0.9
Summary: A command line for creating Pypi projects
Home-page: https://github.com/Haider-Ali-Dev/create-pypi-project
Author: Haider Ali
Author-email: ali075398@gmail.com
License: UNKNOWN
Project-URL: Bug Tracker, https://github.com/Haider-Ali-Dev/create-pypi-project/issues
Keywords: python tool,command line
Platform: UNKNOWN
Classifier: Programming Language :: Python :: 3
Classifier: License :: OSI Approved :: MIT License
Classifier: Operating System :: OS Independent
Requires-Python: >=3.6
License-File: LICENSE
